setup.cfg
setup.py
globomap_driver_acs/__init__.py
globomap_driver_acs/cloudstack.py
globomap_driver_acs/driver.py
globomap_driver_acs/load.py
globomap_driver_acs/rabbitmq.py
globomap_driver_acs/settings.py
globomap_driver_acs/update_handlers.py
globomap_driver_acs.egg-info/PKG-INFO
globomap_driver_acs.egg-info/SOURCES.txt
globomap_driver_acs.egg-info/dependency_links.txt
globomap_driver_acs.egg-info/requires.txt
globomap_driver_acs.egg-info/top_level.txt