Metadata-Version: 1.0
Name: globomap-driver-acs
Version: 0.0.30
Summary: Python library for globomap-driver to get data from Cloudstack
Home-page: https://github.com/globocom/globomap-driver-acs
Author: Victor Mendes Eduardo
Author-email: victor.eduard@corp.globo.com
License: UNKNOWN
Platform: UNKNOWN
